xj_enroll/__init__.py
xj_enroll/admin.py
xj_enroll/apps.py
xj_enroll/models.py
xj_enroll/serializers.py
xj_enroll/service_register.py
xj_enroll/urls.py
xj_enroll/api/[category_apis_del][del_by_sky].py
xj_enroll/api/[classify_apis_del][del_by_sky].py
xj_enroll/api/__init__.py
xj_enroll/api/enroll_apis.py
xj_enroll/api/enroll_statistics_apis.py
xj_enroll/api/enroll_status_code_api.py
xj_enroll/api/rarely_data_list_api.py
xj_enroll/api/record_apis.py
xj_enroll/api/rule_apis.py
xj_enroll/api/subitem_apis.py
xj_enroll/api/subitem_record_apis.py
xj_enroll/api/valuation_api.py
xj_enroll/library/__init__.py
xj_enroll/library/j_valuation/__init__.py
xj_enroll/library/j_valuation/j_base_expression.py
xj_enroll/library/j_valuation/j_expressions.py
xj_enroll/library/j_valuation/j_valuation.py
xj_enroll/service/__init__.py
xj_enroll/service/clock_service.py
xj_enroll/service/enroll_push_service.py
xj_enroll/service/enroll_record_serivce.py
xj_enroll/service/enroll_services.py
xj_enroll/service/enroll_statistics_services.py
xj_enroll/service/enroll_status_code_service.py
xj_enroll/service/enroll_subitem_record_service.py
xj_enroll/service/excel_exporter_service.py
xj_enroll/service/rule_service.py
xj_enroll/service/subitem_extend_service.py
xj_enroll/service/subitem_service.py
xj_enroll/service/valuation_service.py
xj_enroll/utils/__init__.py
xj_enroll/utils/custom_response.py
xj_enroll/utils/custom_tool.py
xj_enroll/utils/j_config.py
xj_enroll/utils/j_dict.py
xj_enroll/utils/j_valuation.py
xj_enroll/utils/join_list.py
xj_enroll/utils/user_wrapper.py
xj_enroll/utils/validator.py
xj_enroll/validator/__init__.py
xj_enroll/validator/category_validator.py
xj_enroll/validator/enroll_validator.py
xj_enroll/validator/record_validator.py
xj_enroll/validator/rule_validator.py
xj_enroll-1.0.231.dist-info/METADATA
xj_enroll-1.0.231.dist-info/WHEEL
xj_enroll-1.0.231.dist-info/top_level.txt
xj_enroll-1.0.231.dist-info/RECORD
