Metadata-Version: 2.1
Name: xj-enroll
Version: 1.0.231
Summary: 报名模块
Author: 赵向明
Author-email: sieyoo@163.com
Maintainer: 孙楷炎
Maintainer-email: sky4834@163.com
License: apache 3.0
